aionxapi/__init__.py
aionxapi/aioportcheck.py
aionxapi/device.py
asyncnxapi/__init__.py
asyncnxapi/device.py
asyncnxapi/xmlhelp.py
aio_nxapi-0.6.0.dist-info/LICENSE
aio_nxapi-0.6.0.dist-info/METADATA
aio_nxapi-0.6.0.dist-info/WHEEL
aio_nxapi-0.6.0.dist-info/RECORD
