Metadata-Version: 2.1
Name: aio-nxapi
Version: 0.6.0
Summary: Cisco NX-API asyncio client
Author: Jeremy Schulman
Requires-Python: >=3.10
Classifier: Programming Language :: Python :: 3
Classifier: Programming Language :: Python :: 3.10
Classifier: Programming Language :: Python :: 3.11
Classifier: Programming Language :: Python :: 3.12
Requires-Dist: httpx (>=0.23.0,<0.24.0)
Requires-Dist: lxml (>=4.9.1,<5.0.0)
